[
  {
    "id": "1023ced3-2c79-4b01-a4a3-b40ec9118c16",
    "data": [
      {
        "text": "hlo",
        "userDefined": false
      }
    ],
    "isTemplate": false,
    "count": 0,
    "lang": "en",
    "updated": 0
  },
  {
    "id": "7bfd0898-ae96-47ae-80d4-e9f840af3d27",
    "data": [
      {
        "text": "hiii",
        "userDefined": false
      }
    ],
    "isTemplate": false,
    "count": 0,
    "lang": "en",
    "updated": 0
  },
  {
    "id": "37a80f22-9457-4130-a62e-63510ba8b1a0",
    "data": [
      {
        "text": "just going to say hi",
        "userDefined": false
      }
    ],
    "isTemplate": false,
    "count": 0,
    "lang": "en",
    "updated": 0
  },
  {
    "id": "d36c8aba-884f-4774-9dd7-dd90f4751d5e",
    "data": [
      {
        "text": "heya",
        "userDefined": false
      }
    ],
    "isTemplate": false,
    "count": 0,
    "lang": "en",
    "updated": 0
  },
  {
    "id": "2e7fdf44-6b2b-4bd6-806b-02946885e3b9",
    "data": [
      {
        "text": "hello hi",
        "userDefined": false
      }
    ],
    "isTemplate": false,
    "count": 0,
    "lang": "en",
    "updated": 0
  },
  {
    "id": "c21cf5b5-7c82-4ac4-8564-d23fe57d4927",
    "data": [
      {
        "text": "howdy",
        "userDefined": false
      }
    ],
    "isTemplate": false,
    "count": 0,
    "lang": "en",
    "updated": 0
  },
  {
    "id": "617e3bf3-4eed-4e97-8af5-084dda430aaa",
    "data": [
      {
        "text": "hey there",
        "userDefined": false
      }
    ],
    "isTemplate": false,
    "count": 0,
    "lang": "en",
    "updated": 0
  },
  {
    "id": "e8bfd0d9-3466-45bf-8a0a-fb59dd598cb2",
    "data": [
      {
        "text": "hi there",
        "userDefined": false
      }
    ],
    "isTemplate": false,
    "count": 1,
    "lang": "en",
    "updated": 0
  },
  {
    "id": "516c7937-933f-4571-b1f6-c48f5fa242c9",
    "data": [
      {
        "text": "greetings",
        "userDefined": false
      }
    ],
    "isTemplate": false,
    "count": 0,
    "lang": "en",
    "updated": 0
  },
  {
    "id": "21843ad2-cd3f-44ed-acf0-973e0b121d0c",
    "data": [
      {
        "text": "hey",
        "userDefined": false
      }
    ],
    "isTemplate": false,
    "count": 0,
    "lang": "en",
    "updated": 0
  },
  {
    "id": "9b7b5d00-b59e-46e2-8051-f2854dde59e0",
    "data": [
      {
        "text": "long time no see",
        "userDefined": false
      }
    ],
    "isTemplate": false,
    "count": 0,
    "lang": "en",
    "updated": 0
  },
  {
    "id": "f2b2c818-e27c-4029-a022-a440501acd86",
    "data": [
      {
        "text": "hello",
        "userDefined": false
      }
    ],
    "isTemplate": false,
    "count": 0,
    "lang": "en",
    "updated": 0
  },
  {
    "id": "29ab1cfd-e665-4b22-bbc6-cd2a52fc8780",
    "data": [
      {
        "text": "lovely day isn\u0027t it",
        "userDefined": false
      }
    ],
    "isTemplate": false,
    "count": 0,
    "lang": "en",
    "updated": 0
  },
  {
    "id": "ab26b5ff-1404-4f37-9282-15922a758e72",
    "data": [
      {
        "text": "I greet you",
        "userDefined": false
      }
    ],
    "isTemplate": false,
    "count": 0,
    "lang": "en",
    "updated": 0
  },
  {
    "id": "7333bb5c-f0a2-4942-aa6c-04fea52595fc",
    "data": [
      {
        "text": "hello again",
        "userDefined": false
      }
    ],
    "isTemplate": false,
    "count": 0,
    "lang": "en",
    "updated": 0
  },
  {
    "id": "e1504294-000d-453a-ad3b-07e8ad31935c",
    "data": [
      {
        "text": "hi",
        "userDefined": false
      }
    ],
    "isTemplate": false,
    "count": 0,
    "lang": "en",
    "updated": 0
  },
  {
    "id": "3b1aab41-5f69-4146-9b21-21454be95ec4",
    "data": [
      {
        "text": "hello there",
        "userDefined": false
      }
    ],
    "isTemplate": false,
    "count": 0,
    "lang": "en",
    "updated": 0
  },
  {
    "id": "c10d195a-9dd7-4d49-8f65-09fc70a5cfe9",
    "data": [
      {
        "text": "a good day",
        "userDefined": false
      }
    ],
    "isTemplate": false,
    "count": 0,
    "lang": "en",
    "updated": 0
  }
]